cuminai/__init__.py
cuminai/chunker.py
cuminai/config.py
cuminai/constants.py
cuminai/contextstores.py
cuminai/creator.py
cuminai/document_loader.py
cuminai/embedding.py
cuminai/tagger.py
cuminai/utils.py
cuminai/validator.py
cuminai-0.0.3.dist-info/entry_points.txt
cuminai-0.0.3.dist-info/LICENSE
cuminai-0.0.3.dist-info/METADATA
cuminai-0.0.3.dist-info/WHEEL
cuminai-0.0.3.dist-info/RECORD
