Metadata-Version: 2.1
Name: cuminai
Version: 0.0.3
Summary: This package contains the Cumin AI Python SDK. Cumin AI is a Managed LLM Frontier Knowledge.
Author: Harshal Priyadarshi
Author-email: harshal@cuminai.com
Requires-Python: >=3.9,<3.13
Classifier: Programming Language :: Python :: 3
Classifier: Programming Language :: Python :: 3.9
Classifier: Programming Language :: Python :: 3.10
Classifier: Programming Language :: Python :: 3.11
Classifier: Programming Language :: Python :: 3.12
Requires-Dist: beautifulsoup4 (>=4.10.0)
Requires-Dist: chardet (>=5.2.0)
Requires-Dist: click (>=8.1.0)
Requires-Dist: langchain-community (>=0.0.10,<0.2.3)
Requires-Dist: langchain_qdrant (>=0.1.0,<0.1.2)
Requires-Dist: langchain_text_splitters (>=0.0.1)
Requires-Dist: qdrant-client (>=1.0.0)
Requires-Dist: tiktoken (>=0.4.0)
Requires-Dist: tqdm (>=4.66.0)
